Metadata-Version: 2.1
Name: ksp.py
Version: 0.0.1
Summary: An API wrapper for KSP.
Home-page: https://github.com/adam757521/ksp.py
Author: adam7100
License: MIT
Download-URL: https://github.com/adam757521/ksp.py/archive/refs/tags/v0.0.1.tar.gz
Keywords: ksp,products,onlineshopping,api,wrapper,python
Platform: UNKNOWN
Classifier: Development Status :: 4 - Beta
Classifier: Intended Audience :: Developers
Classifier: Topic :: Software Development :: Build Tools
Classifier: License :: OSI Approved :: MIT License
Classifier: Programming Language :: Python :: 3
Classifier: Programming Language :: Python :: 3.4
Classifier: Programming Language :: Python :: 3.5
Classifier: Programming Language :: Python :: 3.6
